.gitignore
MANIFEST.in
Pipfile
Pipfile.lock
README.md
setup.cfg
setup.py
scripts/black.sh
scripts/publish.sh
src/declarative_iptables.egg-info/PKG-INFO
src/declarative_iptables.egg-info/SOURCES.txt
src/declarative_iptables.egg-info/dependency_links.txt
src/declarative_iptables.egg-info/top_level.txt
src/iptables/__init__.py
src/iptables/logic.py
src/iptables/models.py
src/iptables/parser.py
src/iptables/tables.py
src/tests/__init__.py
src/tests/test_logic.py
src/tests/test_models.py
src/tests/test_parser.py
src/tests/test_tables.py
src/tests/utils.py
src/tests/files/iptables-save_with-mangle.txt