Metadata-Version: 2.1
Name: declarative-iptables
Version: 0.1.2
Summary: work with iptables in a declarative manner
Home-page: https://github.com/rca/declarative-iptables
Author: Roberto Aguilar
Author-email: roberto.c.aguilar@gmail.com
License: UNKNOWN
Platform: UNKNOWN
